{"count":10,"events":[{"category":"","color":"","end":"10-27-2022 11:33:00","files":[],"id":"239","isallday":false,"links":[],"location":"255 Street name St, City, State 80305","start":"10-27-2022 11:33:00","summary":"Location test","title":"Location test"},{"category":"","color":"","end":"10-27-2022 19:00:00","files":[],"id":"240","isallday":false,"links":[],"location":"https:\/\/listjs.com\/api\/#search","start":"10-27-2022 18:00:00","summary":"Location test","title":"Location test - Online"},{"category":"","color":"","end":"10-31-2022 14:20:00","files":[{"description":"This is just an example document.pdf","url":"https:\/\/www.plusportals.com\/\/Account\/DownloadSchoolResources?storagefilePath=thebrandonacademyrediker-2022-23&fileName=This is just an example document.pdf&storageFileName=b872036b-17b7-435b-b4f0-eafd54aa8b35.pdf&token=64EE210A5F46F06D522C716D4E3B2D09F1BD6A33276436B9505BA181258F55D1"},{"description":"noun-download-4576128.svg","url":"https:\/\/www.plusportals.com\/\/Account\/DownloadSchoolResources?storagefilePath=thebrandonacademyrediker-2022-23&fileName=noun-download-4576128.svg&storageFileName=3bf6602c-ce68-4626-8b50-574fb2ee6177.svg&token=6A8AC64064793B8953CFC8816F6C3593556444622CB0A916F8DD6A3397BC07E7"}],"id":"241","isallday":false,"links":[],"location":"online","start":"10-28-2022 14:20:00","summary":"file summary content","title":"files"},{"category":"Admissions","color":"#4dff00","end":"11-04-2022","files":[],"id":"237","isallday":true,"links":[],"location":"GYM","start":"10-31-2022","summary":"Blah blah blah","title":"Multi Day Single Event"},{"category":"","color":"","end":"10-31-2022","files":[],"id":"238-1","isallday":true,"links":[],"location":"","start":"10-31-2022","summary":"","title":"Multi Day Event That is a REPEATING Event"},{"category":"","color":"","end":"11-01-2022","files":[],"id":"238-2","isallday":true,"links":[],"location":"","start":"11-01-2022","summary":"","title":"Multi Day Event That is a REPEATING Event"},{"category":"","color":"","end":"11-02-2022","files":[],"id":"238-3","isallday":true,"links":[],"location":"","start":"11-02-2022","summary":"","title":"Multi Day Event That is a REPEATING Event"},{"category":"","color":"","end":"11-03-2022","files":[],"id":"238-4","isallday":true,"links":[],"location":"","start":"11-03-2022","summary":"","title":"Multi Day Event That is a REPEATING Event"},{"category":"","color":"","end":"11-04-2022","files":[],"id":"238-5","isallday":true,"links":[],"location":"","start":"11-04-2022","summary":"","title":"Multi Day Event That is a REPEATING Event"},{"category":"","color":"","end":"11-05-2022","files":[],"id":"238-6","isallday":true,"links":[],"location":"","start":"11-05-2022","summary":"","title":"Multi Day Event That is a REPEATING Event"}],"lastitemindex":9,"page":1,"totalcount":10,"totalpages":1}
